geoplot/__init__.py
geoplot/crs.py
geoplot/datasets.py
geoplot/geoplot.py
geoplot/ops.py
geoplot/utils.py
geoplot-0.5.1.dist-info/LICENSE.md
geoplot-0.5.1.dist-info/METADATA
geoplot-0.5.1.dist-info/WHEEL
geoplot-0.5.1.dist-info/top_level.txt
geoplot-0.5.1.dist-info/RECORD
